LICENSE.txt
README.md
setup.cfg
setup.py
v2rayp/.gitignore
v2rayp/__init__.py
v2rayp/__main__.py
v2rayp/__version__.py
v2rayp/requirement.txt
v2rayp/v2rayp.py
v2rayp.egg-info/PKG-INFO
v2rayp.egg-info/SOURCES.txt
v2rayp.egg-info/dependency_links.txt
v2rayp.egg-info/requires.txt
v2rayp.egg-info/top_level.txt
v2rayp/assets/icons/appicon.ico
v2rayp/assets/icons/picon_blue.png
v2rayp/assets/icons/picon_green.png
v2rayp/assets/icons/picon_red.png
v2rayp/assets/icons/picon_yellow.png
v2rayp/assets/sounds/beep.wav
v2rayp/configs/gost_profiles/gost1.json
v2rayp/configs/gost_profiles/grpc-hels9.imconnect.top-41035.json
v2rayp/configs/gost_profiles/heidar_grpc_2053.json
v2rayp/configs/gost_profiles/heidar_wss_2087.json
v2rayp/configs/gost_profiles/ssh_2017.json
v2rayp/configs/gost_profiles/fragment/temp.json
v2rayp/configs/gui/config.json
v2rayp/configs/gui/subscription.json
v2rayp/configs/v2ray_profiles/backups/reality-test-vfbd9h81.json
v2rayp/configs/v2ray_profiles/backups/reality-trojan-2096.json
v2rayp/configs/v2ray_profiles/backups/shahryar-doko.json
v2rayp/configs/v2ray_profiles/backups/trojan-hels9.imconnect.top-34371.json
v2rayp/configs/v2ray_profiles/backups/trojan1-xjiqhd.json
v2rayp/configs/v2ray_profiles/backups/vless_boz.json
v2rayp/configs/v2ray_profiles/backups/vmess_notls-p0unzh3.json
v2rayp/configs/v2ray_profiles/backups/vmess_ws_2083-mef18oix.json
v2rayp/configs/v2ray_profiles/backups/fragment/temp.json
v2rayp/configs/v2ray_profiles/fragment/temp.json
v2rayp/configs/v2ray_profiles/subscriptions/isharifi_codes_v2ray/reality-test-vfbd9h81.json
v2rayp/configs/v2ray_profiles/subscriptions/isharifi_codes_v2ray/shahryar-doko.json
v2rayp/configs/v2ray_profiles/subscriptions/isharifi_codes_v2ray/shahryar-trojan1-reality.json
v2rayp/configs/v2ray_profiles/subscriptions/isharifi_codes_v2ray/trojan-grpc-r85l64s3v3.json
v2rayp/configs/v2ray_profiles/subscriptions/isharifi_codes_v2ray/trojan1-xjiqhd.json
v2rayp/configs/v2ray_profiles/subscriptions/isharifi_codes_v2ray/vless-grpc-reality.json
v2rayp/configs/v2ray_profiles/subscriptions/isharifi_codes_v2ray/vmess_notls-p0unzh3.json
v2rayp/libs/Chisel_Interface.py
