Metadata-Version: 2.1
Name: v2rayp
Version: 0.7b115
Summary: An efficient and versatile multiplatform project, serving as a v2rayn substitute for Windows, while seamlessly functioning on Mac and Linux, featuring fragmentation support and multi-threaded capabilities.
Home-page: https://github.com/iblockchaincyberchain/v2rayp
Author: iBlockchain
Author-email: iman.minstry@gmail.com
License: MIT
Keywords: Fragmentation,V2Ray,multiplatform,VPN,Proxy
Classifier: Development Status :: 3 - Alpha
Classifier: Intended Audience :: Developers
Classifier: Topic :: Software Development :: Build Tools
Classifier: License :: OSI Approved :: MIT License
Classifier: Programming Language :: Python :: 3.7
Classifier: Programming Language :: Python :: 3.8
Classifier: Programming Language :: Python :: 3.9
Classifier: Programming Language :: Python :: 3.10
Classifier: Programming Language :: Python :: 3.11
Classifier: Programming Language :: Python :: 3.12
License-File: LICENSE.txt
Requires-Dist: PySimpleGUI
Requires-Dist: psgtray
Requires-Dist: requests
Requires-Dist: pyperclip
Requires-Dist: psutil
Requires-Dist: qrcode
Requires-Dist: setuptools
